<?xml version="1.0" encoding="utf-8" ?><dwsync><file name="testimonial3.png" server="cirillic.beget.tech" local="3691049664" remote="3706427940" Dst="-1" /><file name="testimonial2.png" server="cirillic.beget.tech" local="3691049664" remote="3706427940" Dst="-1" /><file name="testimonial1.png" server="cirillic.beget.tech" local="3691049664" remote="3706427940" Dst="-1" /><file name="client6.png" server="cirillic.beget.tech" local="3691049664" remote="3706427940" Dst="-1" /><file name="client4.png" server="cirillic.beget.tech" local="3691049664" remote="3706427940" Dst="-1" /><file name="client5.png" server="cirillic.beget.tech" local="3691049664" remote="3706427940" Dst="-1" /><file name="client1.png" server="cirillic.beget.tech" local="3691049664" remote="3706427940" Dst="-1" /><file name="client2.png" server="cirillic.beget.tech" local="3691049664" remote="3706427940" Dst="-1" /><file name="client3.png" server="cirillic.beget.tech" local="3691049664" remote="3706427940" Dst="-1" /></dwsync>